acs_cli/__init__.py
acs_cli/cli.py
acs_cli/sync.py
acs_cli/templates/blueprint.md
acs_cli/templates/journal.md
acs_cli/templates/rules.md
acs_cli/templates/vibe-guide.md
agentic_std-0.2.0.dist-info/METADATA
agentic_std-0.2.0.dist-info/WHEEL
agentic_std-0.2.0.dist-info/entry_points.txt
agentic_std-0.2.0.dist-info/licenses/LICENSE
agentic_std-0.2.0.dist-info/RECORD
