Metadata-Version: 2.4
Name: agentic-std
Version: 0.2.0
Summary: Agentic Coding Standard CLI - Scaffold .agent/ directories for AI-ready codebases
Project-URL: Homepage, https://github.com/Alaa-Taieb/agentic-std
Project-URL: Repository, https://github.com/Alaa-Taieb/agentic-std
Author: Alaa Taieb
License-Expression: MIT
License-File: LICENSE
Keywords: agentic,ai,cli,coding,scaffold,standards
Classifier: Development Status :: 3 - Alpha
Classifier: Environment :: Console
Classifier: Intended Audience :: Developers
Classifier: License :: OSI Approved :: MIT License
Classifier: Programming Language :: Python :: 3
Classifier: Programming Language :: Python :: 3.10
Classifier: Programming Language :: Python :: 3.11
Classifier: Programming Language :: Python :: 3.12
Classifier: Topic :: Software Development :: Code Generators
Requires-Python: >=3.10
Requires-Dist: httpx>=0.27.0
Requires-Dist: typer[all]>=0.9.0
